README.md
pyproject.toml
src/pullnix/__init__.py
src/pullnix/cli.py
src/pullnix/config.py
src/pullnix/repository.py
src/pullnix.egg-info/PKG-INFO
src/pullnix.egg-info/SOURCES.txt
src/pullnix.egg-info/dependency_links.txt
src/pullnix.egg-info/entry_points.txt
src/pullnix.egg-info/requires.txt
src/pullnix.egg-info/top_level.txt
tests/test_cli.py
tests/test_config.py
tests/test_repository.py