Metadata-Version: 2.1
Name: pullnix
Version: 0.0.3
Summary: A pull based NixOS deployment tool
Author-email: Andreas Wuerl <andi@tryb.de>
Project-URL: Homepage, https://github.com/wuan/pullnix
Project-URL: Bug Tracker, https://github.com/wuan/pullnix/issues
Classifier: Programming Language :: Python :: 3
Classifier: License :: OSI Approved :: MIT License
Classifier: Operating System :: OS Independent
Requires-Python: >=3.7
Provides-Extra: test
